{
	"author": ["Vadim Zaytsev"],
	"back": "SLE-2013",
	"booktitle": "Proceedings of the Sixth International Conference on Software Language Engineering",
	"booktitleshort": "SLE",
	"crossref": "conf/sle/2013",
	"dblpkey": "conf/sle/Zaytsev13",
	"doi": "10.1007/978-3-319-02654-1_7",
	"editor": [
		"Martin Erwig",
		"Richard F. Paige",
		"Eric Van Wyk"
	],
	"ee": "http://dx.doi.org/10.1007/978-3-319-02654-1_7",
	"isbn": "978-3-319-02653-4",
	"pages": "117-136",
	"past": [
		"1. Ammeraal, L.: On the Design of Programming Languages Including MINI ALGOL 68. In: Mühlbacher, J.R. (ed.) GI 1975. LNCS, vol. 34, pp. 500–504. Springer, Heidelberg (1975)",
		"dblp:ACM-SE-2010-Batarseh",
		"book:Beck1996",
		"bibsleigh:SE/2012/ICSE-2012/ICSE-2012-Butler",
		"book:Chomsky1957",
		"dblp:IC-1959-Chomsky",
		"dblp:COMSIS-2010-CrepinsekKMCFR",
		"8. van Emde Boas, P.: Resistance is Futile; Formal Linguistic Observations on De-sign Patterns. Technical Report ILLC-CT-97-02, Institute for Logic, Language and Computation, University of Amsterdam (1997)",
		"bibsleigh:SLE/2011/SLE-2011/SLE-2011-FischerLZ",
		"bibsleigh:OOP/1997/ECOOP-1997/ECOOP-1997-FlorijnMW",
		"book:Fowler2002",
		"book:Fowler2011",
		"book:Gamma1994",
		"bibsleigh:OOP/2005/OOPSLA-2005/OOPSLA-2005-GilM",
		"15. Greibach, S.A.: A New Normal-Form Theorem for Context-Free Phrase Structure Grammars. Journal of the ACM 12(1), 42–52 (1965)",
		"16. Hoare, C.A.R.: Hints on Programming Language Design. Technical report, Stan-ford University, Stanford, CA, USA (1973)",
		"17. Johnson, S.C.: YACC—Yet Another Compiler Compiler. Computer Science Tech-nical Report 32, AT&T Bell Laboratories, Murray Hill, New Jersey (1975)",
		"bibsleigh:EVOL/2001/ICSM-2001/ICSM-2001-JongeM",
		"book:Kleppe2008",
		"dblp:ToSEM-2005-KlintLV",
		"bibsleigh:SE/2009/GTTSE-2009/GTTSE-2009-KlintSV",
		"bibsleigh:FM/2001/FME-2001/FME-2001-Lammel",
		"dblp:SPE-2001-LaemmelV",
		"bibsleigh:SLE/2001/LDTA-2001/LDTA-2001-LammelW",
		"bibsleigh:EVOL/2009/SCAM-J-2009/SCAM-J-2009-LammelZ11",
		"bibsleigh:OOP/2001/OOPSLA-2001/OOPSLA-2001-LanzaD",
		"dblp:CSUR-2005-MernikHS",
		"dblp:JSME-2004-PowerM",
		"29. Thies, A., Roth, C.: Recommending Rename Refactorings. In: Proceedings of the Second International Workshop on Recommendation Systems for Software Engi- neering, RSSE 2010, pp. 1–5. ACM (2010)",
		"book:Voelter2013",
		"31. van Wijngaarden, A.: Orthogonal Design and Description of a Formal Language. In: MR, vol. 76. SMC (1965)",
		"bibsleigh:SE/1997/ICSE-1997/ICSE-1997-Wile",
		"33. Wirth,N.:OntheDesignofProgrammingLanguages.In:IFIPCongress,pp.386–393 (1974)",
		"dblp:CACM-1977-Wirth",
		"dblp:CoRR-2011-Zaytsev",
		"bibsleigh:SAC/2012/SAC-2012/SAC-2012-Zaytsev",
		"bibsleigh:SLE/2012/LDTA-2012/LDTA-2012-Zaytsev",
		"dblp:CoRR-2012-Zaytsev",
		"dblp:SCP-2015-Zaytsev",
		"dblp:CoRR-2015-Zaytsev",
		"bibsleigh:SLE/2010/SLE-2010/SLE-2010-ZaytsevL",
		"42. Zaytsev, V., Lämmel, R., van der Storm, T., Renggli, L., Wachsmuth, G.: Software Language Processing Suite 6 (2008-2013), http://slps.github.io"
	],
	"publisher": "Springer International Publishing",
	"publishershort": "Springer",
	"series": "Lecture Notes in Computer Science",
	"seriesshort": "LNCS",
	"stemmed": ["micropattern", "in", "grammar"],
	"tag": ["grammarware"],
	"title": "Micropatterns in Grammars",
	"type": "inproceedings",
	"venue": "SLE",
	"volume": 8225,
	"year": 2013
}